README.md
setup.py
ConBased/ConBased_2D_Funs.py
ConBased/ConBased_3D_Funs.py
ConBased/ConBased_3D_Funs_LBV.py
ConBased/Detect_ConBased.py
ConBased/Detect_Files.py
ConBased/Detect_Files_Funs.py
ConBased/Evaluate.py
ConBased/Evaluate_2D_Funs.py
ConBased/Evaluate_3D_Funs.py
ConBased/Generate.py
ConBased/Generate_2D_Funs.py
ConBased/Generate_3D_Funs.py
ConBased/Test_File.py
ConBased/__init__.py
ConBased.egg-info/PKG-INFO
ConBased.egg-info/SOURCES.txt
ConBased.egg-info/dependency_links.txt
ConBased.egg-info/top_level.txt