Metadata-Version: 2.1
Name: ConBased
Version: 0.0.6
Summary: A connectivity-based method for detecting clumpy structures in molecular clouds
Author: Jiang Yu
Author-email: yujiang@pmo.ac.cn
